app_enabler/__init__.py
app_enabler/__main__.py
app_enabler/cli.py
app_enabler/django.py
app_enabler/enable.py
app_enabler/errors.py
app_enabler/install.py
app_enabler/patcher.py
django_app_enabler-0.5.0.dist-info/licenses/LICENSE
django_app_enabler-0.5.0.dist-info/METADATA
django_app_enabler-0.5.0.dist-info/WHEEL
django_app_enabler-0.5.0.dist-info/entry_points.txt
django_app_enabler-0.5.0.dist-info/top_level.txt
django_app_enabler-0.5.0.dist-info/RECORD
