Metadata-Version: 2.4
Name: django-app-enabler
Version: 0.5.0
Summary: Autoconfigurator for django applications
Home-page: https://github.com/nephila/django-app-enabler
Author: Nephila
Author-email: info@nephila.it
License: BSD
Project-URL: Documentation, https://django-app-enabler.readthedocs.io/
Classifier: Development Status :: 4 - Beta
Classifier: Framework :: Django
Classifier: Intended Audience :: Developers
Classifier: Natural Language :: English
Classifier: Framework :: Django
Classifier: Framework :: Django :: 4.2
Classifier: Programming Language :: Python :: 3
Classifier: Programming Language :: Python :: 3.10
Classifier: Programming Language :: Python :: 3.11
Requires-Python: >=3.10
License-File: LICENSE
Requires-Dist: astor
Requires-Dist: click<8.2.0
Provides-Extra: docs
Requires-Dist: django<5.0; extra == "docs"
Requires-Dist: sphinx-click; extra == "docs"
Requires-Dist: sphinx-rtd-theme; extra == "docs"
Dynamic: license-file
